lbuild/__init__.py
lbuild/api.py
lbuild/buildlog.py
lbuild/collector.py
lbuild/config.py
lbuild/environment.py
lbuild/exception.py
lbuild/facade.py
lbuild/filter.py
lbuild/format.py
lbuild/logger.py
lbuild/main.py
lbuild/module.py
lbuild/node.py
lbuild/option.py
lbuild/parser.py
lbuild/query.py
lbuild/repository.py
lbuild/utils.py
lbuild/builder/__init__.py
lbuild/builder/dependency.py
lbuild/resources/configuration.xsd
lbuild/vcs/__init__.py
lbuild/vcs/common.py
lbuild/vcs/git.py
lbuild-1.21.8.dist-info/LICENSE.txt
lbuild-1.21.8.dist-info/METADATA
lbuild-1.21.8.dist-info/WHEEL
lbuild-1.21.8.dist-info/entry_points.txt
lbuild-1.21.8.dist-info/top_level.txt
lbuild-1.21.8.dist-info/RECORD
