Metadata-Version: 2.1
Name: lbuild
Version: 1.21.8
Summary: Generic, modular code generator using the Jinja2 template engine.
Home-page: https://github.com/modm-io/lbuild
Author: Fabian Greif, Niklas Hauser
Author-email: fabian.greif@rwth-aachen.de, niklas@salkinium.com
License: BSD
Keywords: library builder generator
Classifier: Development Status :: 5 - Production/Stable
Classifier: Environment :: Console
Classifier: Intended Audience :: Developers
Classifier: License :: OSI Approved :: BSD License
Classifier: Natural Language :: English
Classifier: Operating System :: OS Independent
Classifier: Programming Language :: Python
Classifier: Programming Language :: Python :: 3
Classifier: Topic :: Software Development
Classifier: Topic :: Software Development :: Code Generators
Classifier: Topic :: Software Development :: Embedded Systems
Requires-Python: >=3.8.0
License-File: LICENSE.txt
Requires-Dist: lxml
Requires-Dist: jinja2
Requires-Dist: gitpython >=2.1.11
Requires-Dist: anytree >=2.6.0
Provides-Extra: test
Requires-Dist: testfixtures ; extra == 'test'
Requires-Dist: coverage ; extra == 'test'
